setup.py
moniBenzi_probability/Binomialdistribution.py
moniBenzi_probability/Gaussiandistribution.py
moniBenzi_probability/Generaldistribution.py
moniBenzi_probability/__init__.py
moniBenzi_probability.egg-info/PKG-INFO
moniBenzi_probability.egg-info/SOURCES.txt
moniBenzi_probability.egg-info/dependency_links.txt
moniBenzi_probability.egg-info/not-zip-safe
moniBenzi_probability.egg-info/top_level.txt